{
  "surahNumber": "99",
  "surahName": "Zilzâl Suresi",
  "ayats": [
    {
      "ayahNumber": "1",
      "ayahText": "Yer o yaman sarsıntı ile sarsıldığı,"
    },
    {
      "ayahNumber": "2",
      "ayahText": "Yer (bağrındaki) ağırlıklarını çıkardığı,"
    },
    {
      "ayahNumber": "3",
      "ayahText": "Ve insan: \"Ona ne oluyor?\" dediği zaman!"
    },
    {
      "ayahNumber": "4",
      "ayahText": "İşte o gün (yer), haberlerini söyler."
    },
    {
      "ayahNumber": "5",
      "ayahText": "Çünkü Rabbin ona vahyetmiştir (onun için başından geçenleri anlatır)."
    },
    {
      "ayahNumber": "6",
      "ayahText": "O gün insanlar, ayrı ayrı gruplar halinde (Yüce Divana) çıkarlar ki, yaptıkları işler kendilerine gösterilsin."
    },
    {
      "ayahNumber": "7",
      "ayahText": "Artık kim zerre ağırlığınca hayır yapmışsa onu görür."
    },
    {
      "ayahNumber": "8",
      "ayahText": "Ve kim zerre ağırlığınca şer yapmışsa onu görür."
    }
  ]
}