{
  "kafirun": {
    "surahNumber": "109",
    "surahNameTr": "Kâfirûn Suresi",
    "ayats": [
      {
        "ayahNumber": "1",
        "ayahText": "De ki: Ey kâfirler!"
      },
      {
        "ayahNumber": "2",
        "ayahText": "Ben sizin ibadet ettiklerinize ibadet etmem."
      },
      {
        "ayahNumber": "3",
        "ayahText": "Siz de benim ibadet ettiğime ibadet etmiyorsunuz."
      },
      {
        "ayahNumber": "4",
        "ayahText": "Ben sizin ibadet ettiklerinize asla ibadet edecek değilim."
      },
      {
        "ayahNumber": "5",
        "ayahText": "Siz de benim ibadet ettiğime ibadet etmezsiniz."
      },
      {
        "ayahNumber": "6",
        "ayahText": "O halde sizin dininiz size, benim dinim bana."
      }
    ]
  }
}