{
  "karia": {
    "surahNumber": "101",
    "surahNameTr": "Kâria Suresi",
    "ayats": [
      {
        "ayahNumber": "1",
        "ayahText": "Kâria! (Çarpacak kıyamet) Nedir o kâria? Kârianın ne olduğunu sen bilir misin?"
      },
      {
        "ayahNumber": "2",
        "ayahText": "Kâria! (Çarpacak kıyamet) Nedir o kâria? Kârianın ne olduğunu sen bilir misin?"
      },
      {
        "ayahNumber": "3",
        "ayahText": "Kâria! (Çarpacak kıyamet) Nedir o kâria? Kârianın ne olduğunu sen bilir misin?"
      },
      {
        "ayahNumber": "4",
        "ayahText": "O gün insanlar yayılmış pervaneler gibi olurlar."
      },
      {
        "ayahNumber": "5",
        "ayahText": "Dağlar atılmış renkli yünler gibi olur."
      },
      {
        "ayahNumber": "6",
        "ayahText": "O gün kimin tartıları ağır basarsa o, hoşnut olacağı bir hayat içindedir."
      },
      {
        "ayahNumber": "7",
        "ayahText": "O gün kimin tartıları ağır basarsa o, hoşnut olacağı bir hayat içindedir."
      },
      {
        "ayahNumber": "8",
        "ayahText": "Kimin tartıları hafif gelirse, onun anası da (varacağı yer, sığınacağı durağı) hâviye (uçurum)dır."
      },
      {
        "ayahNumber": "9",
        "ayahText": "Kimin tartıları hafif gelirse, onun anası da (varacağı yer, sığınacağı durağı) hâviye (uçurum)dır."
      },
      {
        "ayahNumber": "10",
        "ayahText": "O uçurumun ne olduğunu sen nereden bileceksin?"
      },
      {
        "ayahNumber": "11",
        "ayahText": "O, kızgın bir ateştir."
      }
    ]
  }
}