{
  "zilzal": {
    "surahNumber": "99",
    "surahNameTr": "Zilzâl Suresi",
    "ayats": [
      {
        "ayahNumber": "1",
        "ayahText": "Yer o yaman sarsıntı ile sarsıldığı,"
      },
      {
        "ayahNumber": "2",
        "ayahText": "Yer, içindeki ağırlıkları çıkarıp dışarı attığı,"
      },
      {
        "ayahNumber": "3",
        "ayahText": "Ve insan: \"Ona ne oluyor?\" dediği zaman."
      },
      {
        "ayahNumber": "4",
        "ayahText": "O gün yer, Rabbinin ona vahyetmesiyle haberlerini anlatacaktır."
      },
      {
        "ayahNumber": "5",
        "ayahText": "O gün yer, Rabbinin ona vahyetmesiyle haberlerini anlatacaktır."
      },
      {
        "ayahNumber": "6",
        "ayahText": "O gün insanlar, amellerinin karşılığı kendilerine gösterilmek üzere bölük bölük çıkacaklardır."
      },
      {
        "ayahNumber": "7",
        "ayahText": "Her kim zerre kadar hayır işlemişse onu görecektir."
      },
      {
        "ayahNumber": "8",
        "ayahText": "Her kim, zerre kadar şer işlemişse onu görecektir."
      }
    ]
  }
}